pyrology
