Metadata-Version: 2.1
Name: pyrology
Version: 0.0.35
Summary: Namespace
Home-page: UNKNOWN
Author: Cesare Barberis
License: UNKNOWN
Platform: UNKNOWN
License-File: LICENSE
